[
  {
    "name": "NH-Amundi 필승 코리아 증권투자신탁[주식] Cla  C-P2e(퇴직연금)",
    "fullName": "NH-Amundi 필승 코리아 증권투자신탁[주식] Cla  C-P2e(퇴직연금) 높은위험 2",
    "riskLevel": "높은위험 2",
    "ref": "ref-dnjzkrx9k2c"
  },
  {
    "name": "미래에셋코어테크증권자투자신탁(주식) 종류C-P2E",
    "fullName": "미래에셋코어테크증권자투자신탁(주식) 종류C-P2E 매우높은위험 1",
    "riskLevel": "매우높은위험 1",
    "ref": "ref-vm4ye9kacnl"
  },
  {
    "name": "하나IT코리아증권자투자신탁(제1호)[주식] 종류 C-P2E",
    "fullName": "하나IT코리아증권자투자신탁(제1호)[주식] 종류 C-P2E 높은위험 2",
    "riskLevel": "높은위험 2",
    "ref": "ref-79rjgozzyj4"
  },
  {
    "name": "삼성퇴직연금KOSPI200증권자투자신탁제1호[주식]Ce",
    "fullName": "삼성퇴직연금KOSPI200증권자투자신탁제1호[주식]Ce 높은위험 2",
    "riskLevel": "높은위험 2",
    "ref": "ref-1wy61au5dx8"
  },
  {
    "name": "KB스타 한국 인덱스 증권 자투자신탁(주식) C-퇴직e 클래스",
    "fullName": "KB스타 한국 인덱스 증권 자투자신탁(주식) C-퇴직e 클래스 높은위험 2",
    "riskLevel": "높은위험 2",
    "ref": "ref-f6u75mm23wq"
  },
  {
    "name": "미래에셋KRX300인덱스증권투자신탁(주식-파생형)종류C-P2e",
    "fullName": "미래에셋KRX300인덱스증권투자신탁(주식-파생형)종류C-P2e 높은위험 2",
    "riskLevel": "높은위험 2",
    "ref": "ref-fz5gajzl3sd"
  },
  {
    "name": "미래에셋연금한국헬스케어증권자투자신탁1호(주식)C-P2e",
    "fullName": "미래에셋연금한국헬스케어증권자투자신탁1호(주식)C-P2e 매우높은위험 1",
    "riskLevel": "매우높은위험 1",
    "ref": "ref-ypq27qeeabm"
  },
  {
    "name": "대신 KOSPI200 인덱스 증권 자투자신탁[주식] Cla C-Pe",
    "fullName": "대신 KOSPI200 인덱스 증권 자투자신탁[주식] Cla C-Pe 높은위험 2",
    "riskLevel": "높은위험 2",
    "ref": "ref-mvlokwjovs"
  },
  {
    "name": "한국투자퇴직연금한국의힘증권자투자신탁1호(주식) C-e 클래스",
    "fullName": "한국투자퇴직연금한국의힘증권자투자신탁1호(주식) C-e 클래스 높은위험 2",
    "riskLevel": "높은위험 2",
    "ref": "ref-rwpvjp182xk"
  },
  {
    "name": "DB바이오헬스케어증권자투자신탁제1호(주식)C-P2E",
    "fullName": "DB바이오헬스케어증권자투자신탁제1호(주식)C-P2E 높은위험 2",
    "riskLevel": "높은위험 2",
    "ref": "ref-731o7a8sdit"
  },
  {
    "name": "미래에셋그린뉴딜인덱스증권자투자신탁(주식)종류C-P2e",
    "fullName": "미래에셋그린뉴딜인덱스증권자투자신탁(주식)종류C-P2e 매우높은위험 1",
    "riskLevel": "매우높은위험 1",
    "ref": "ref-1z7ajla6dmd"
  },
  {
    "name": "마이다스신성장기업포커스증권자투자신탁(주식) C-Pe2클래스",
    "fullName": "마이다스신성장기업포커스증권자투자신탁(주식) C-Pe2클래스 높은위험 2",
    "riskLevel": "높은위험 2",
    "ref": "ref-qky7ho3vu5m"
  },
  {
    "name": "마이다스액티브가치증권투자회사(주식)종류 C-Pe2",
    "fullName": "마이다스액티브가치증권투자회사(주식)종류 C-Pe2 높은위험 2",
    "riskLevel": "높은위험 2",
    "ref": "ref-c4dy2jard8"
  },
  {
    "name": "KB액티브배당증권자투자신탁(주식)C-퇴직e",
    "fullName": "KB액티브배당증권자투자신탁(주식)C-퇴직e 높은위험 2",
    "riskLevel": "높은위험 2",
    "ref": "ref-6kmzid23hg9"
  },
  {
    "name": "미래에셋퇴직연금코어밸류증권자투자신탁1호(주식)C-P2e",
    "fullName": "미래에셋퇴직연금코어밸류증권자투자신탁1호(주식)C-P2e 높은위험 2",
    "riskLevel": "높은위험 2",
    "ref": "ref-u7lw4i0n7wf"
  },
  {
    "name": "iM에셋월드골드증권자투자신탁(주식-재간접형)(UH)(C-Rpe)",
    "fullName": "iM에셋월드골드증권자투자신탁(주식-재간접형)(UH)(C-Rpe) 매우높은위험 1",
    "riskLevel": "매우높은위험 1",
    "ref": "ref-hiuwrgxydig"
  },
  {
    "name": "한화한국오퍼튜니티증권 자투자신탁(주식)P-E",
    "fullName": "한화한국오퍼튜니티증권 자투자신탁(주식)P-E 높은위험 2",
    "riskLevel": "높은위험 2",
    "ref": "ref-i0s64iw6kxg"
  },
  {
    "name": "삼성배당주장기증권투자신탁 제1호[주식](Cpe(퇴직연금))",
    "fullName": "삼성배당주장기증권투자신탁 제1호[주식](Cpe(퇴직연금)) 높은위험 2",
    "riskLevel": "높은위험 2",
    "ref": "ref-yydvvt7yayr"
  },
  {
    "name": "삼성글로벌반도체증권자투자신탁UH[주식]_Cpe(퇴직)",
    "fullName": "삼성글로벌반도체증권자투자신탁UH[주식]_Cpe(퇴직) 매우높은위험 1",
    "riskLevel": "매우높은위험 1",
    "ref": "ref-r39dicbv5k"
  },
  {
    "name": "마이다스 책임투자 증권투자신탁(주식)C-Pe2",
    "fullName": "마이다스 책임투자 증권투자신탁(주식)C-Pe2 높은위험 2",
    "riskLevel": "높은위험 2",
    "ref": "ref-dwh8p14khc"
  }
]